{"TOUR": {"1": {"idtournoi": 1, "idtour": "1T1", "nom": "round1", "date_debut": "2022-05-03 23:28:09", "date_fin": "2022-05-03 23:35:47", "etat": "Termin\u00e9", "matchs": []}, "2": {"idtournoi": 1, "idtour": "1T2", "nom": "round2", "date_debut": "2022-05-03 23:35:17", "date_fin": "2022-05-03 23:41:48", "etat": "Termin\u00e9", "matchs": []}, "3": {"idtournoi": 1, "idtour": "1T3", "nom": "round3", "date_debut": "2022-05-03 23:41:36", "date_fin": "2022-05-03 23:42:25", "etat": "Termin\u00e9", "matchs": []}, "4": {"idtournoi": 1, "idtour": "1T4", "nom": "round4", "date_debut": "2022-05-03 23:41:36", "date_fin": "2022-05-03 23:52:28", "etat": "Termin\u00e9", "matchs": []}, "5": {"idtournoi": 2, "idtour": "2T1", "nom": "round1", "date_debut": "2022-05-03 23:41:36", "date_fin": "2022-05-03 23:53:56", "etat": "Termin\u00e9", "matchs": []}, "6": {"idtournoi": 2, "idtour": "2T2", "nom": "round2", "date_debut": "2022-05-03 23:41:36", "date_fin": "2022-05-03 23:55:08", "etat": "Termin\u00e9", "matchs": []}, "7": {"idtournoi": 2, "idtour": "2T3", "nom": "round3", "date_debut": "2022-05-03 23:54:26", "date_fin": "2022-05-03 23:55:37", "etat": "Termin\u00e9", "matchs": []}, "8": {"idtournoi": 2, "idtour": "2T4", "nom": "round4", "date_debut": "2022-05-03 23:54:26", "date_fin": "2022-05-03 23:55:59", "etat": "Termin\u00e9", "matchs": []}, "9": {"idtournoi": 3, "idtour": "3T1", "nom": "round1", "date_debut": "2022-05-04 00:00:44", "date_fin": "2022-05-04 00:02:32", "etat": "Termin\u00e9", "matchs": [[[1, 10], [5, 20]], [[2, 20], [6, 10]], [[3, 20], [8, 10]], [[4, 30], [9, 10]]]}, "10": {"idtournoi": 3, "idtour": "3T2", "nom": "round2", "date_debut": "2022-05-04 00:00:44", "date_fin": "2022-05-04 00:02:48", "etat": "Termin\u00e9", "matchs": [[[2, 10], [3, 20]], [[4, 30], [5, 10]], [[1, 20], [6, 20]], [[8, 10], [9, 20]]]}, "11": {"idtournoi": 3, "idtour": "3T3", "nom": "round3", "date_debut": "2022-05-04 00:00:44", "date_fin": "", "etat": "en cours", "matchs": []}}, "TOURNOI": {"1": {"idtournoi": 1, "nom": "TEST", "lieu": "", "date_debut": "", "date_fin": "2022-05-03", "tours": ["1T1", "1T3", "1T4"], "joueurs": [1, 10, 3, 4, 5, 6, 9, 8], "timecontrol": "BLITZ", "description": "", "nbtours": 4}, "2": {"idtournoi": 2, "nom": "DEUX", "lieu": "", "date_debut": "", "date_fin": "2022-05-04", "tours": ["2T1", "2T2", "2T3", "2T4"], "joueurs": [1, 2, 3, 4, 5, 6, 9, 8], "timecontrol": "BULLET", "description": "", "nbtours": 4}, "3": {"idtournoi": 3, "nom": "TROIS", "lieu": "", "date_debut": "", "date_fin": "", "tours": ["3T1", "3T2", "3T3"], "joueurs": [1, 2, 3, 4, 5, 6, 9, 8], "timecontrol": "BLITZ", "description": "", "nbtours": 4}}, "JOUEUR": {"1": {"idjoueur": 1, "nom": "UN", "prenom": "j", "date_naissance": "", "sexe": "", "classement": 1, "points": 0.5}, "2": {"idjoueur": 2, "nom": "DEUX", "prenom": "j", "date_naissance": "", "sexe": "", "classement": 2, "points": 1.0}, "3": {"idjoueur": 3, "nom": "TROIS", "prenom": "j", "date_naissance": "", "sexe": "", "classement": 3, "points": 2.0}, "4": {"idjoueur": 4, "nom": "QUATRE", "prenom": "j", "date_naissance": "", "sexe": "", "classement": 4, "points": 2.0}, "5": {"idjoueur": 5, "nom": "CINQ", "prenom": "j", "date_naissance": "", "sexe": "", "classement": 5, "points": 1.0}, "6": {"idjoueur": 6, "nom": "SIX", "prenom": "j", "date_naissance": "", "sexe": "", "classement": 6, "points": 0.5}, "7": {"idjoueur": 7, "nom": "DRPT", "prenom": "j", "date_naissance": "", "sexe": "", "classement": 7, "points": 2.5}, "8": {"idjoueur": 8, "nom": "HUIT", "prenom": "j", "date_naissance": "", "sexe": "", "classement": 8, "points": 0.0}, "9": {"idjoueur": 9, "nom": "SEPT", "prenom": "j", "date_naissance": "", "sexe": "", "classement": 9, "points": 1.0}, "10": {"idjoueur": 10, "nom": "DEUX ", "prenom": "j", "date_naissance": "", "sexe": "", "classement": 2, "points": 0.5}}, "MATCH": {"1": {"idtournoi": "1", "idtour": "1T1", "idmatch": "M1", "joueur1": 1, "joueur2": 5, "score1": 10, "score2": 20}, "2": {"idtournoi": "1", "idtour": "1T1", "idmatch": "M2", "joueur1": 10, "joueur2": 6, "score1": 30, "score2": 10}, "3": {"idtournoi": "1", "idtour": "1T1", "idmatch": "M3", "joueur1": 3, "joueur2": 8, "score1": 20, "score2": 20}, "4": {"idtournoi": "1", "idtour": "1T1", "idmatch": "M4", "joueur1": 4, "joueur2": 9, "score1": 10, "score2": 20}, "5": {"idtournoi": "1", "idtour": "1T3", "idmatch": "M1", "joueur1": 6, "joueur2": 9, "score1": 10, "score2": 20}, "6": {"idtournoi": "1", "idtour": "1T3", "idmatch": "M2", "joueur1": 1, "joueur2": 3, "score1": 30, "score2": 10}, "7": {"idtournoi": "1", "idtour": "1T3", "idmatch": "M3", "joueur1": 5, "joueur2": 8, "score1": 20, "score2": 20}, "8": {"idtournoi": "1", "idtour": "1T3", "idmatch": "M4", "joueur1": 10, "joueur2": 4, "score1": 10, "score2": 20}, "9": {"idtournoi": "2", "idtour": "2T1", "idmatch": "M1", "joueur1": 1, "joueur2": 5, "score1": 10, "score2": 20}, "10": {"idtournoi": "2", "idtour": "2T1", "idmatch": "M2", "joueur1": 2, "joueur2": 6, "score1": 30, "score2": 10}, "11": {"idtournoi": "2", "idtour": "2T1", "idmatch": "M3", "joueur1": 3, "joueur2": 8, "score1": 20, "score2": 20}, "12": {"idtournoi": "2", "idtour": "2T1", "idmatch": "M4", "joueur1": 4, "joueur2": 9, "score1": 10, "score2": 20}, "13": {"idtournoi": "2", "idtour": "2T2", "idmatch": "M1", "joueur1": 2, "joueur2": 4, "score1": 10, "score2": 20}, "14": {"idtournoi": "2", "idtour": "2T2", "idmatch": "M2", "joueur1": 5, "joueur2": 8, "score1": 30, "score2": 10}, "15": {"idtournoi": "2", "idtour": "2T2", "idmatch": "M3", "joueur1": 1, "joueur2": 3, "score1": 20, "score2": 20}, "16": {"idtournoi": "2", "idtour": "2T2", "idmatch": "M4", "joueur1": 6, "joueur2": 9, "score1": 10, "score2": 20}, "17": {"idtournoi": "2", "idtour": "2T3", "idmatch": "M1", "joueur1": 4, "joueur2": 5, "score1": 10, "score2": 20}, "18": {"idtournoi": "2", "idtour": "2T3", "idmatch": "M2", "joueur1": 8, "joueur2": 2, "score1": 30, "score2": 10}, "19": {"idtournoi": "2", "idtour": "2T3", "idmatch": "M3", "joueur1": 3, "joueur2": 6, "score1": 20, "score2": 20}, "20": {"idtournoi": "2", "idtour": "2T3", "idmatch": "M4", "joueur1": 1, "joueur2": 9, "score1": 10, "score2": 20}, "21": {"idtournoi": "2", "idtour": "2T4", "idmatch": "M1", "joueur1": 8, "joueur2": 4, "score1": 10, "score2": 20}, "22": {"idtournoi": "2", "idtour": "2T4", "idmatch": "M2", "joueur1": 2, "joueur2": 3, "score1": 30, "score2": 10}, "23": {"idtournoi": "3", "idtour": "3T1", "idmatch": "M1", "joueur1": 1, "joueur2": 5, "score1": 10, "score2": 20}, "24": {"idtournoi": "3", "idtour": "3T1", "idmatch": "M2", "joueur1": 2, "joueur2": 6, "score1": 30, "score2": 10}, "25": {"idtournoi": "3", "idtour": "3T1", "idmatch": "M3", "joueur1": 3, "joueur2": 8, "score1": 20, "score2": 20}, "26": {"idtournoi": "3", "idtour": "3T1", "idmatch": "M4", "joueur1": 4, "joueur2": 9, "score1": 10, "score2": 20}, "27": {"idtournoi": "3", "idtour": "3T2", "idmatch": "M1", "joueur1": 2, "joueur2": 3, "score1": 10, "score2": 20}, "28": {"idtournoi": "3", "idtour": "3T2", "idmatch": "M2", "joueur1": 4, "joueur2": 5, "score1": 30, "score2": 10}, "29": {"idtournoi": "3", "idtour": "3T2", "idmatch": "M3", "joueur1": 1, "joueur2": 6, "score1": 20, "score2": 20}, "30": {"idtournoi": "3", "idtour": "3T2", "idmatch": "M4", "joueur1": 8, "joueur2": 9, "score1": 10, "score2": 20}}}